[{"id":"test-a-Wadz","date":"2018-05-26T01:50:57.755Z","mediaFilename":"smidgeo_headshot.jpg","caption":"Smidgeo!","altText":"A picture of Smidgeo!","postedToPersistence":true,"htmlFragment":"<li class=\"pane\">\n  <div class=\"time-stamp entry-meta\">\n    <a href=\"test-a-Wadz.html\">\n      <time datetime=\"2018-05-26T01:50:57.755Z\">2018-5-25 21:50:57</time>\n    </a>\n  </div><img src=\"media/smidgeo_headshot.jpg\" alt=\"A picture of Smidgeo!\"></video><div class=\"media-caption entry-meta\">Smidgeo!</div></li>","postedSingleVideoPage":true}]